_multiprocess/__init__.py
multiprocess/__info__.py
multiprocess/__init__.py
multiprocess/connection.py
multiprocess/context.py
multiprocess/forkserver.py
multiprocess/heap.py
multiprocess/managers.py
multiprocess/pool.py
multiprocess/popen_fork.py
multiprocess/popen_forkserver.py
multiprocess/popen_spawn_posix.py
multiprocess/popen_spawn_win32.py
multiprocess/process.py
multiprocess/queues.py
multiprocess/reduction.py
multiprocess/resource_sharer.py
multiprocess/resource_tracker.py
multiprocess/shared_memory.py
multiprocess/sharedctypes.py
multiprocess/spawn.py
multiprocess/synchronize.py
multiprocess/util.py
multiprocess/dummy/__init__.py
multiprocess/dummy/connection.py
multiprocess/tests/__init__.py
multiprocess/tests/__main__.py
multiprocess/tests/mp_fork_bomb.py
multiprocess/tests/mp_preload.py
multiprocess/tests/test_multiprocessing_fork.py
multiprocess/tests/test_multiprocessing_forkserver.py
multiprocess/tests/test_multiprocessing_main_handling.py
multiprocess/tests/test_multiprocessing_spawn.py
multiprocess-0.70.18.dist-info/licenses/COPYING
multiprocess-0.70.18.dist-info/licenses/LICENSE
multiprocess-0.70.18.dist-info/METADATA
multiprocess-0.70.18.dist-info/WHEEL
multiprocess-0.70.18.dist-info/top_level.txt
multiprocess-0.70.18.dist-info/RECORD
