Metadata-Version: 2.2
Name: multiprocess
Version: 0.70.18
Summary: better multiprocessing and multithreading in Python
Home-page: https://github.com/uqfoundation/multiprocess
Download-URL: https://pypi.org/project/multiprocess/#files
Author: Mike McKerns
Author-email: mmckerns@uqfoundation.org
Maintainer: Mike McKerns
Maintainer-email: mmckerns@uqfoundation.org
License: BSD-3-Clause
Project-URL: Documentation, http://multiprocess.rtfd.io
Project-URL: Source Code, https://github.com/uqfoundation/multiprocess
Project-URL: Bug Tracker, https://github.com/uqfoundation/multiprocess/issues
Platform: Linux
Platform: Windows
Platform: Mac
Classifier: Development Status :: 5 - Production/Stable
Classifier: Intended Audience :: Developers
Classifier: Intended Audience :: Science/Research
Classifier: License :: OSI Approved :: BSD License
Classifier: Programming Language :: Python :: 3
Classifier: Programming Language :: Python :: 3.8
Classifier: Programming Language :: Python :: 3.9
Classifier: Programming Language :: Python :: 3.10
Classifier: Programming Language :: Python :: 3.11
Classifier: Programming Language :: Python :: 3.12
Classifier: Programming Language :: Python :: 3.13
Classifier: Programming Language :: Python :: Implementation :: CPython
Classifier: Programming Language :: Python :: Implementation :: PyPy
Classifier: Topic :: Scientific/Engineering
Classifier: Topic :: Software Development
Requires-Python: >=3.8
License-File: LICENSE
License-File: COPYING
Requires-Dist: dill>=0.4.0
Dynamic: author
Dynamic: author-email
Dynamic: classifier
Dynamic: description
Dynamic: download-url
Dynamic: home-page
Dynamic: license
Dynamic: maintainer
Dynamic: maintainer-email
Dynamic: platform
Dynamic: project-url
Dynamic: requires-dist
Dynamic: requires-python
Dynamic: summary
